autosel/__init__.py
autosel/main.py
autosel-0.0.6.dist-info/LICENSE
autosel-0.0.6.dist-info/METADATA
autosel-0.0.6.dist-info/WHEEL
autosel-0.0.6.dist-info/top_level.txt
autosel-0.0.6.dist-info/RECORD
