Metadata-Version: 2.1
Name: autosel
Version: 0.0.6
Summary: Autosel is a Python package that automates sending emails, Whatsapp text, images, videos, and audio messages along with other functionalities like creating a group and spam bot.
Home-page: https://github.com/unKNOWN-G/autosel
Author: Giri
Author-email: <karnatisaivenkatagiri@gmail.com>
License: MIT
Keywords: autosel,automate,whatsapp,email,spam,bot,python,selenium
Platform: UNKNOWN
Classifier: License :: OSI Approved :: MIT License
Classifier: Programming Language :: Python :: 3
Classifier: Development Status :: 3 - Alpha
Classifier: Intended Audience :: Education
Classifier: Operating System :: OS Independent
Requires-Dist: Selenium
Requires-Dist: gTTS
